Workbook

Sheet Lisez-moi
A1: Backlog consolidé — Plateforme de gestion de projets et pilotage de portefeuille (PPM) — prisme secteur public
A3: Objet | B3: Backlog unique consolidant les exigences des 3 cahiers de spécifications (Project Monitor, Sciforma, Microsoft Planner/Project), dédoublonnées et priorisées selon le dossier de synthèse du 4 juillet 2026, avec le prisme 'pouvoir adjudicateur / entreprise publique'.
A4: Logique de priorisation
A5: P0 — Socle | B5: Intersection des 3 outils (dossier §4) : planifier, visualiser, consolider, collaborer. Must, Lot 1.
A6: P1 — Cœur PPM & SI public | B6: Bloc PPM partagé PM+Sciforma (demande, capacité, budgets pluriannuels, temps, risques, comités — dossier §5.1) + exigences critiques des insights (I2 interface comptable, I3 capacité, I4 souveraineté, I5 pérennité, I9 traçabilité) + chantiers SI.
A7: P2 — Différenciant | B7: Fonctionnalités rares d'un seul outil (dossier §6) : what-if, agent IA exécutant, DLP sur tâches, on-premise, IA souveraine... À activer selon positionnement.
A8: P3 — Innovation publique | B8: Bonus B1-B8 (dossier §7) : commande publique, subventions, AP/CP, livrables d'instance, transparence, archivage probant, valeur publique, format ouvert.
A10: Colonnes
A11: Origine | B11: Socle 3/3, 2/3, Différenciant [outil], Bonus Bn, Insight In, NFR, Contexte public FR.
A12: Complexité | B12: S (jours), M (1-2 sprints), L (3-6 sprints), XL (chantier).
A13: Épique E13 | B13: Chantiers SI hors produit : décisions d'architecture, consultation/marché, gouvernance, adoption.
A15: Notes souveraineté | B15: PP-046 (on-premise) et PP-035 (hébergement FR/UE) deviennent des exigences fermes si des portefeuilles sensibles existent (cf. PP-028/PP-064).
A17: Total items | B17: =COUNTA(Backlog!A2:A200) -> 70

Sheet Backlog
A1: ID | B1: Épique | C1: Item | D1: Description | E1: Priorité | F1: MoSCoW | G1: Lot cible | H1: Origine | I1: Justification (dossier) | J1: Complexité
A2: PP-001 | B2: E02 Planification | C2: Gantt, dépendances, jalons | D2: Planification interactive multi-projets : WBS, dépendances, jalons, planification automatique. | E2: P0 | F2: Must | G2: Lot 1 | H2: Socle 3/3 | I2: Dossier §4 : présent chez les 3 | J2: L
A3: PP-002 | B3: E02 Planification | C3: Chemin critique | D3: Calcul et visualisation du chemin critique pour prioriser ressources et affectations. | E3: P0 | F3: Must | G3: Lot 1 | H3: Socle 3/3 | I3: Dossier §4 | J3: M
A4: PP-003 | B4: E02 Planification | C4: Vues multiples | D4: Tableau/Kanban, liste, calendrier, chronologie ; filtres et regroupements ; export Excel. | E4: P0 | F4: Must | G4: Lot 1 | H4: Socle 3/3 | I4: Dossier §4 | J4: M
A5: PP-004 | B5: E05 Portefeuille & comités | C5: Vue portefeuille consolidée | D5: Vision 360° multi-projets : santé, avancement, phases, jalons et dates clés, avec drill-down. | E5: P0 | F5: Must | G5: Lot 1 | H5: Socle 3/3 | I5: Dossier §4 | J5: L
A6: PP-005 | B6: E02 Planification | C6: Modèles de projets | D6: Bibliothèque de modèles réutilisables et gouvernés (méthodes internes transposables). | E6: P0 | F6: Must | G6: Lot 1 | H6: Socle 3/3 | I6: Dossier §4 | J6: M
A7: PP-006 | B7: E05 Portefeuille & comités | C7: Tableaux de bord personnalisables | D7: Tableaux synthétiques et détaillés par profil, avec alertes sur points de tension. | E7: P0 | F7: Must | G7: Lot 1 | H7: Socle 3/3 | I7: Dossier §4 | J7: L
A8: PP-007 | B8: E03 Ressources & temps | C8: Ressources et affectations | D8: Affectation des ressources aux tâches/projets, visualisation des charges. | E8: P0 | F8: Must | G8: Lot 1 | H8: Socle 3/3 | I8: Dossier §4 | J8: L
A9: PP-008 | B9: E04 Budgets & finances | C9: Coûts au niveau projet | D9: Suivi des coûts par projet : prévu, engagé, réalisé. | E9: P0 | F9: Must | G9: Lot 1 | H9: Socle 3/3 | I9: Dossier §4 | J9: M
A10: PP-009 | B10: E06 Collaboration & tâches | C10: Collaboration contextuelle | D10: Échanges rattachés aux tâches/projets (mentions, fils, notifications ciblées). | E10: P0 | F10: Must | G10: Lot 1 | H10: Socle 3/3 | I10: Dossier §4 | J10: M
A11: PP-010 | B11: E08 Gouvernance & sécurité | C11: Droits par rôle et périmètre | D11: Rôles fins (élus, direction, PMO, MOA, MOE, métiers, externes) avec périmètres de visibilité. | E11: P0 | F11: Must | G11: Lot 1 | H11: Socle 3/3 | I11: Dossier §4 | J11: L
A12: PP-011 | B12: E11 NFR | C12: Cloud/SaaS et RGPD | D12: Déploiement SaaS ; RGPD avec DPA ; chiffrement transit/repos ; disponibilité >= 99,5 %. | E12: P0 | F12: Must | G12: Lot 1 | H12: Socle 3/3 + NFR des 3 cahiers | I12: Cahiers ENF | J12: L
... A71: PP-070 | B71: E13 Chantiers SI | C71: Audit RGAA | D71: Faire auditer la conformité RGAA de l'outil retenu et publier la déclaration d'accessibilité. | E71: P1 | F71: Must | G71: Lot 2 | H71: Contexte public FR | I71: Obligation légale ; prolonge PP-012 | J71: M

Sheet Synthèse
A1: Synthèse du backlog
A3: Par priorité | B3: Nombre | D3: Par lot | E3: Nombre
A4: P0 — Socle (3/3) | B4: =COUNTIF(Backlog!E:E,"P0") -> 12 | D4: Lot 1 | E4: =COUNTIF(Backlog!G:G,"Lot 1") -> 26
A5: P1 — Cœur PPM & SI public | B5: =COUNTIF(Backlog!E:E,"P1") -> 33 | D5: Lot 2 | E5: =COUNTIF(Backlog!G:G,"Lot 2") -> 21
A6: P2 — Différenciant | B6: =COUNTIF(Backlog!E:E,"P2") -> 17 | D6: Lot 3 | E6: =COUNTIF(Backlog!G:G,"Lot 3") -> 9
A7: P3 — Innovation publique | B7: =COUNTIF(Backlog!E:E,"P3") -> 8 | D7: Lot 4 | E7: =COUNTIF(Backlog!G:G,"Lot 4") -> 14
A8: Total | B8: =SUM(B4:B7) -> 70 | D8: Total | E8: =SUM(E4:E7) -> 70
A10: Par épique
A11: Épique | B11: Items | C11: dont Must
A12: E01 Demande & arbitrage | B12: =COUNTIF(Backlog!B:B,"E01 Demande & arbitrage") -> 6 | C12: =COUNTIFS(Backlog!B:B,"E01 Demande & arbitrage",Backlog!F:F,"Must") -> 3
A13: E02 Planification | B13: =COUNTIF(Backlog!B:B,"E02 Planification") -> 6 | C13: =COUNTIFS(Backlog!B:B,"E02 Planification",Backlog!F:F,"Must") -> 5
A14: E03 Ressources & temps | B14: =COUNTIF(Backlog!B:B,"E03 Ressources & temps") -> 3 | C14: =COUNTIFS(Backlog!B:B,"E03 Ressources & temps",Backlog!F:F,"Must") -> 3
A15: E04 Budgets & finances | B15: =COUNTIF(Backlog!B:B,"E04 Budgets & finances") -> 3 | C15: =COUNTIFS(Backlog!B:B,"E04 Budgets & finances",Backlog!F:F,"Must") -> 2
A16: E05 Portefeuille & comités | B16: =COUNTIF(Backlog!B:B,"E05 Portefeuille & comités") -> 6 | C16: =COUNTIFS(Backlog!B:B,"E05 Portefeuille & comités",Backlog!F:F,"Must") -> 3
A17: E06 Collaboration & tâches | B17: =COUNTIF(Backlog!B:B,"E06 Collaboration & tâches") -> 3 | C17: =COUNTIFS(Backlog!B:B,"E06 Collaboration & tâches",Backlog!F:F,"Must") -> 1
A18: E07 IA & agents | B18: =COUNTIF(Backlog!B:B,"E07 IA & agents") -> 4 | C18: =COUNTIFS(Backlog!B:B,"E07 IA & agents",Backlog!F:F,"Must") -> 0
A19: E08 Gouvernance & sécurité | B19: =COUNTIF(Backlog!B:B,"E08 Gouvernance & sécurité") -> 7 | C19: =COUNTIFS(Backlog!B:B,"E08 Gouvernance & sécurité",Backlog!F:F,"Must") -> 5
A20: E09 Intégration SI | B20: =COUNTIF(Backlog!B:B,"E09 Intégration SI") -> 5 | C20: =COUNTIFS(Backlog!B:B,"E09 Intégration SI",Backlog!F:F,"Must") -> 2
A21: E10 Licences & réversibilité | B21: =COUNTIF(Backlog!B:B,"E10 Licences & réversibilité") -> 4 | C21: =COUNTIFS(Backlog!B:B,"E10 Licences & réversibilité",Backlog!F:F,"Must") -> 3
A22: E11 NFR | B22: =COUNTIF(Backlog!B:B,"E11 NFR") -> 5 | C22: =COUNTIFS(Backlog!B:B,"E11 NFR",Backlog!F:F,"Must") -> 4
A23: E12 Innovation | B23: =COUNTIF(Backlog!B:B,"E12 Innovation") -> 8 | C23: =COUNTIFS(Backlog!B:B,"E12 Innovation",Backlog!F:F,"Must") -> 0
A24: E13 Chantiers SI | B24: =COUNTIF(Backlog!B:B,"E13 Chantiers SI") -> 10 | C24: =COUNTIFS(Backlog!B:B,"E13 Chantiers SI",Backlog!F:F,"Must") -> 9
A25: Total | B25: =SUM(B12:B24) -> 70 | C25: =SUM(C12:C24) -> 40
